[
  {
    "timestamp": "2026-04-02T22:12:36.068Z",
    "sha": "ed319e0",
    "source": {
      "files": 5,
      "loc": 140
    },
    "tests": {
      "files": 5,
      "loc": 220,
      "ratio": "1.57"
    },
    "eslintDisable": 0,
    "skippedTests": 0,
    "governanceScripts": 19
  },
  {
    "timestamp": "2026-04-02T22:16:14.938Z",
    "sha": "ed319e0",
    "source": {
      "files": 5,
      "loc": 140
    },
    "tests": {
      "files": 5,
      "loc": 220,
      "ratio": "1.57"
    },
    "eslintDisable": 0,
    "skippedTests": 0,
    "governanceScripts": 20
  }
]
